{
  "model": {
    "type": "minecraft:select",
    "property": "minecraft:component",
    "component": "minecraft:custom_data",
    "cases": [
      {
        "when": {"PublicBukkitValues":{"slimefun:slimefun_item":"WITHER_PROOF_OBSIDIAN"}},
        "model": {
          "type": "model",
          "model": "slimefun:slimefun/technical_components/wither_proof_obsidian"
        }
      },
      {
        "when": {"PublicBukkitValues":{"slimefun:slimefun_item":"WITHER_ASSEMBLER"}},
        "model": {
          "type": "model",
          "model": "slimefun:slimefun/energy/wither_assembler"
        }
      },
      {
        "when": {"PublicBukkitValues":{"slimefun:slimefun_item":"MOD_PLATE"}},
        "model": {
          "type": "model",
          "model": "slimetinker:materials/mod_plate"
        }
      }
    ],
    "fallback": {
      "type": "model",
      "model": "block/obsidian"
    }
  }
}